diameter_clustering/__init__.py
diameter_clustering/base.py
diameter_clustering/dist_matrix.py
diameter_clustering/greedy.py
diameter_clustering/leader.py
diameter_clustering/qt.py
diameter_clustering/timer.py
diameter_clustering-0.0.1.dist-info/LICENSE
diameter_clustering-0.0.1.dist-info/METADATA
diameter_clustering-0.0.1.dist-info/WHEEL
diameter_clustering-0.0.1.dist-info/top_level.txt
diameter_clustering-0.0.1.dist-info/RECORD
