Metadata-Version: 2.1
Name: diameter-clustering
Version: 0.0.1
Summary: Clustering with maximum distance between points inside clusters
Home-page: https://github.com/antklen/diameter-clustering
Author: Anton Klenitskiy
Author-email: ant-klen@yandex.ru
License: UNKNOWN
Platform: UNKNOWN
Classifier: Programming Language :: Python :: 3
Classifier: License :: OSI Approved :: MIT License
Classifier: Operating System :: OS Independent
Classifier: Development Status :: 3 - Alpha
Requires-Dist: numpy
Requires-Dist: numpy-groupies
Requires-Dist: scikit-learn
Requires-Dist: scipy
Requires-Dist: tqdm
